LICENSE
README.md
setup.py
null_bot_api/__init__.py
null_bot_api/abc.py
null_bot_api/api.py
null_bot_api/const.py
null_bot_api/exceptions.py
null_bot_api.egg-info/PKG-INFO
null_bot_api.egg-info/SOURCES.txt
null_bot_api.egg-info/dependency_links.txt
null_bot_api.egg-info/requires.txt
null_bot_api.egg-info/top_level.txt
null_bot_api/categories/__init__.py
null_bot_api/categories/base.py
null_bot_api/categories/experts.py
null_bot_api/categories/testers.py
null_bot_api/categories/users.py
null_bot_api/categories/vk.py
null_bot_api/models/__init__.py
null_bot_api/models/experts/__init__.py
null_bot_api/models/experts/get_card.py
null_bot_api/models/experts/get_info.py
null_bot_api/models/testers/__init__.py
null_bot_api/models/testers/get_info.py
null_bot_api/models/users/__init__.py
null_bot_api/models/users/get_all.py
null_bot_api/models/users/get_info.py
null_bot_api/models/users/get_stickers.py
null_bot_api/models/vk/__init__.py
null_bot_api/models/vk/get_olymp.py