Metadata-Version: 2.1
Name: null-bot-api
Version: 1.0.0
Summary: Null Bot API wrapper
Home-page: https://github.com/lordralinc/null_bot_api
Author: lordralinc
License: MIT
Platform: UNKNOWN
Classifier: Programming Language :: Python :: 3.7
Classifier: Programming Language :: Python :: 3.8
Classifier: Programming Language :: Python :: 3.9
Classifier: Operating System :: OS Independent
License-File: LICENSE
